image_manipulator_thx/__init__.py
image_manipulator_thx/processing/__init__.py
image_manipulator_thx/processing/combination.py
image_manipulator_thx/processing/transformation.py
image_manipulator_thx/utils/__init__.py
image_manipulator_thx/utils/io.py
image_manipulator_thx/utils/plot.py
image_manipulator_thx-0.0.1.dist-info/METADATA
image_manipulator_thx-0.0.1.dist-info/WHEEL
image_manipulator_thx-0.0.1.dist-info/top_level.txt
image_manipulator_thx-0.0.1.dist-info/RECORD
