Metadata-Version: 2.1
Name: image-manipulator-thx
Version: 0.0.1
Summary: pacote de manipulação de imagem - Projeto 2 DIO
Home-page: https://github.com/rafanthx13/criar-pacote-python-process-de-imagens
Author: Rafael Assis
Author-email: rafa-assis@hotmail.com
License: UNKNOWN
Platform: UNKNOWN
Requires-Python: >=3.6
Requires-Dist: numpy
Requires-Dist: setuptools
Requires-Dist: matplotlib
Requires-Dist: scikit-image
